tesseract_python/__init__.py
tesseract_python/tesseract/bin/tesseract
tesseract_python/tesseract/include/tesseract/apitypes.h
tesseract_python/tesseract/include/tesseract/baseapi.h
tesseract_python/tesseract/include/tesseract/basedir.h
tesseract_python/tesseract/include/tesseract/capi.h
tesseract_python/tesseract/include/tesseract/errcode.h
tesseract_python/tesseract/include/tesseract/fileerr.h
tesseract_python/tesseract/include/tesseract/genericvector.h
tesseract_python/tesseract/include/tesseract/helpers.h
tesseract_python/tesseract/include/tesseract/host.h
tesseract_python/tesseract/include/tesseract/ltrresultiterator.h
tesseract_python/tesseract/include/tesseract/memry.h
tesseract_python/tesseract/include/tesseract/ndminx.h
tesseract_python/tesseract/include/tesseract/ocrclass.h
tesseract_python/tesseract/include/tesseract/osdetect.h
tesseract_python/tesseract/include/tesseract/pageiterator.h
tesseract_python/tesseract/include/tesseract/params.h
tesseract_python/tesseract/include/tesseract/platform.h
tesseract_python/tesseract/include/tesseract/publictypes.h
tesseract_python/tesseract/include/tesseract/renderer.h
tesseract_python/tesseract/include/tesseract/resultiterator.h
tesseract_python/tesseract/include/tesseract/serialis.h
tesseract_python/tesseract/include/tesseract/strngs.h
tesseract_python/tesseract/include/tesseract/tesscallback.h
tesseract_python/tesseract/include/tesseract/thresholder.h
tesseract_python/tesseract/include/tesseract/unichar.h
tesseract_python/tesseract/include/tesseract/unicharmap.h
tesseract_python/tesseract/include/tesseract/unicharset.h
tesseract_python/tesseract/lib/pkgconfig/tesseract.pc
tesseract_python/tesseract/share/tessdata/eng.traineddata
tesseract_python/tesseract/share/tessdata/pdf.ttf
tesseract_python/tesseract/share/tessdata/configs/ambigs.train
tesseract_python/tesseract/share/tessdata/configs/api_config
tesseract_python/tesseract/share/tessdata/configs/bigram
tesseract_python-3.5.1.dist-info/DESCRIPTION.rst
tesseract_python-3.5.1.dist-info/METADATA
tesseract_python-3.5.1.dist-info/RECORD
tesseract_python-3.5.1.dist-info/WHEEL
tesseract_python-3.5.1.dist-info/metadata.json
tesseract_python-3.5.1.dist-info/top_level.txt
