Metadata-Version: 2.0
Name: tesseract-python
Version: 3.5.1
Summary: Self-contained Python module to Tesseract.
Home-page: https://github.com/ic/tesseract-python
Author: Eric Platon
Author-email: zaraki@gmx.com
License: MIT
Platform: UNKNOWN
Classifier: Environment :: Console
Classifier: Intended Audience :: Developers
Classifier: Intended Audience :: Education
Classifier: Intended Audience :: Information Technology
Classifier: Intended Audience :: Science/Research
Classifier: License :: OSI Approved :: MIT License
Classifier: Operating System :: POSIX
Classifier: Operating System :: Unix
Classifier: Programming Language :: Python
Classifier: Programming Language :: Python :: 2
Classifier: Programming Language :: Python :: 2.7
Classifier: Programming Language :: Python :: 3
Classifier: Programming Language :: Python :: 3.6
Classifier: Programming Language :: C++
Classifier: Topic :: Scientific/Engineering
Classifier: Topic :: Software Development
Requires-Dist: Pillow (==5.0.0)
Requires-Dist: pytesseract (==0.2.0)
